jeremy_test/__init__.py
jeremy_test/_nbdev.py
jeremy_test/core.py
test_pypi/__init__.py
test_pypi/_nbdev.py
test_pypi/core.py
jeremy_test-0.0.2.dist-info/LICENSE
jeremy_test-0.0.2.dist-info/METADATA
jeremy_test-0.0.2.dist-info/WHEEL
jeremy_test-0.0.2.dist-info/entry_points.txt
jeremy_test-0.0.2.dist-info/top_level.txt
jeremy_test-0.0.2.dist-info/RECORD
