Metadata-Version: 2.1
Name: jeremy-test
Version: 0.0.2
Summary: A python library
Home-page: https://github.com/jeremytee97/test_pypi/tree/master/
Author: Jeremy
Author-email: jeremytee97@gmail.com
License: Apache Software License 2.0
Keywords: python
Platform: UNKNOWN
Classifier: Development Status :: 3 - Alpha
Classifier: Intended Audience :: Developers
Classifier: License :: OSI Approved :: Apache Software License
Classifier: Natural Language :: English
Classifier: Programming Language :: Python :: 3.6
Classifier: Programming Language :: Python :: 3.7
Classifier: Programming Language :: Python :: 3.8
Requires-Python: >=3.6
